inpher_xor_vault-0.1.0.dist-info/METADATA
inpher_xor_vault-0.1.0.dist-info/WHEEL
inpher_xor_vault-0.1.0.dist-info/license_files/LICENSE
xor_vault/__init__.py
xor_vault/xor_vault.abi3.so
inpher_xor_vault-0.1.0.dist-info/RECORD
