Metadata-Version: 2.1
Name: inpher-xor-vault
Version: 0.1.0
License-File: LICENSE
Summary: Library used to reconstruct secret shared results transfered via xor-vault. Don't use this lib directly, use xor-py.
Keywords: inpher,vault
Author: Florian Duraffourg, Sergiu Carpov
Maintainer: Florian Duraffourg, Sergiu Carpov
Requires-Python: >=3.8
Project-URL: homepage, https://inpher.io
Project-URL: documentation, https://dev.inpher.io/xor/xor-py/
